LICENSE
README.md
hptk.py
setup.py
hptk.egg-info/PKG-INFO
hptk.egg-info/SOURCES.txt
hptk.egg-info/dependency_links.txt
hptk.egg-info/top_level.txt