Metadata-Version: 2.1
Name: hptk
Version: 1.20211219
Summary: hpformula for lyy
Author: lyy
Author-email: 
License: MIT
License-File: LICENSE
